odoo9_addon_sale_exception-9.0.1.1.0-py2.7-nspkg.pth
odoo9_addon_sale_exception-9.0.1.1.0.dist-info/top_level.txt
odoo9_addon_sale_exception-9.0.1.1.0.dist-info/WHEEL
odoo9_addon_sale_exception-9.0.1.1.0.dist-info/RECORD
odoo9_addon_sale_exception-9.0.1.1.0.dist-info/metadata.json
odoo9_addon_sale_exception-9.0.1.1.0.dist-info/DESCRIPTION.rst
odoo9_addon_sale_exception-9.0.1.1.0.dist-info/METADATA
odoo9_addon_sale_exception-9.0.1.1.0.dist-info/namespace_packages.txt
odoo_addons/sale_exception/__openerp__.py
odoo_addons/sale_exception/__init__.py
odoo_addons/sale_exception/README.rst
odoo_addons/sale_exception/security/ir.model.access.csv
odoo_addons/sale_exception/models/sale.py
odoo_addons/sale_exception/models/__init__.py
odoo_addons/sale_exception/i18n/ja.po
odoo_addons/sale_exception/i18n/lv.po
odoo_addons/sale_exception/i18n/zh_CN.po
odoo_addons/sale_exception/i18n/sale_exceptions.pot
odoo_addons/sale_exception/i18n/uk.po
odoo_addons/sale_exception/i18n/es_AR.po
odoo_addons/sale_exception/i18n/ko.po
odoo_addons/sale_exception/i18n/ru.po
odoo_addons/sale_exception/i18n/gl_ES.po
odoo_addons/sale_exception/i18n/pt.po
odoo_addons/sale_exception/i18n/fr_CH.po
odoo_addons/sale_exception/i18n/it.po
odoo_addons/sale_exception/i18n/es.po
odoo_addons/sale_exception/i18n/nl_BE.po
odoo_addons/sale_exception/i18n/ar.po
odoo_addons/sale_exception/i18n/lt.po
odoo_addons/sale_exception/i18n/tr.po
odoo_addons/sale_exception/i18n/sr.po
odoo_addons/sale_exception/i18n/es_PY.po
odoo_addons/sale_exception/i18n/mk.po
odoo_addons/sale_exception/i18n/hr.po
odoo_addons/sale_exception/i18n/bg.po
odoo_addons/sale_exception/i18n/es_EC.po
odoo_addons/sale_exception/i18n/zh_TW.po
odoo_addons/sale_exception/i18n/hu.po
odoo_addons/sale_exception/i18n/gl.po
odoo_addons/sale_exception/i18n/ca.po
odoo_addons/sale_exception/i18n/es_CR.po
odoo_addons/sale_exception/i18n/he.po
odoo_addons/sale_exception/i18n/es_CO.po
odoo_addons/sale_exception/i18n/sl.po
odoo_addons/sale_exception/i18n/sr@latin.po
odoo_addons/sale_exception/i18n/th.po
odoo_addons/sale_exception/i18n/es_PE.po
odoo_addons/sale_exception/i18n/es_ES.po
odoo_addons/sale_exception/i18n/cs.po
odoo_addons/sale_exception/i18n/pt_PT.po
odoo_addons/sale_exception/i18n/eu.po
odoo_addons/sale_exception/i18n/nb.po
odoo_addons/sale_exception/i18n/da.po
odoo_addons/sale_exception/i18n/et.po
